craps_pkg/__init__.py
craps_pkg/craps_pkg.py
craps_pkg_sharnajh-0.1.126.dist-info/METADATA
craps_pkg_sharnajh-0.1.126.dist-info/WHEEL
craps_pkg_sharnajh-0.1.126.dist-info/top_level.txt
craps_pkg_sharnajh-0.1.126.dist-info/RECORD
